[{"idRevelationType":"Mekah","idNameTranslation":"Pembukaan","number":1,"name":"سُورَةُ ٱلْفَاتِحَةِ","englishName":"Al-Faatiha","englishNameTranslation":"The Opening","revelationType":"Meccan","numberOfAyahs":7},{"idRevelationType":"Madinah","idNameTranslation":"Sapi Betina","number":2,"name":"سورة البقرة","englishName":"Al-Baqara","englishNameTranslation":"The Cow","revelationType":"Medinan","numberOfAyahs":286},{"idRevelationType":"Madinah","idNameTranslation":"Keluarga Imran","number":3,"name":"سورة آل عمران","englishName":"Aal-i-Imraan","englishNameTranslation":"The Family of Imraan","revelationType":"Medinan","numberOfAyahs":200},{"idRevelationType":"Madinah","idNameTranslation":"Wanita","number":4,"name":"سورة النساء","englishName":"An-Nisaa","englishNameTranslation":"The Women","revelationType":"Medinan","numberOfAyahs":176},{"idRevelationType":"Madinah","idNameTranslation":"Hidangan","number":5,"name":"سورة المائدة","englishName":"Al-Maaida","englishNameTranslation":"The Table","revelationType":"Medinan","numberOfAyahs":120},{"idRevelationType":"Mekah","idNameTranslation":"Binatang Ternak","number":6,"name":"سورة الأنعام","englishName":"Al-An'aam","englishNameTranslation":"The Cattle","revelationType":"Meccan","numberOfAyahs":165},{"idRevelationType":"Mekah","idNameTranslation":"Tempat Tertinggi","number":7,"name":"سورة الأعراف","englishName":"Al-A'raaf","englishNameTranslation":"The Heights","revelationType":"Meccan","numberOfAyahs":206},{"idRevelationType":"Madinah","idNameTranslation":"Rampasan Perang","number":8,"name":"سورة الأنفال","englishName":"Al-Anfaal","englishNameTranslation":"The Spoils of War","revelationType":"Medinan","numberOfAyahs":75},{"idRevelationType":"Madinah","idNameTranslation":"Pengampunan","number":9,"name":"سورة التوبة","englishName":"At-Tawba","englishNameTranslation":"The Repentance","revelationType":"Medinan","numberOfAyahs":129},{"idRevelationType":"Mekah","idNameTranslation":"Yunus","number":10,"name":"سورة يونس","englishName":"Yunus","englishNameTranslation":"Jonas","revelationType":"Meccan","numberOfAyahs":109},{"idRevelationType":"Mekah","idNameTranslation":"Hud","number":11,"name":"سورة هود","englishName":"Hud","englishNameTranslation":"Hud","revelationType":"Meccan","numberOfAyahs":123},{"idRevelationType":"Mekah","idNameTranslation":"Yusuf","number":12,"name":"سورة يوسف","englishName":"Yusuf","englishNameTranslation":"Joseph","revelationType":"Meccan","numberOfAyahs":111},{"idRevelationType":"Madinah","idNameTranslation":"Guruh","number":13,"name":"سورة الرعد","englishName":"Ar-Ra'd","englishNameTranslation":"The Thunder","revelationType":"Medinan","numberOfAyahs":43},{"idRevelationType":"Mekah","idNameTranslation":"Ibrahim","number":14,"name":"سورة ابراهيم","englishName":"Ibrahim","englishNameTranslation":"Abraham","revelationType":"Meccan","numberOfAyahs":52},{"idRevelationType":"Mekah","idNameTranslation":"Hijr","number":15,"name":"سورة الحجر","englishName":"Al-Hijr","englishNameTranslation":"The Rock","revelationType":"Meccan","numberOfAyahs":99},{"idRevelationType":"Mekah","idNameTranslation":"Lebah","number":16,"name":"سورة النحل","englishName":"An-Nahl","englishNameTranslation":"The Bee","revelationType":"Meccan","numberOfAyahs":128},{"idRevelationType":"Mekah","idNameTranslation":"Memperjalankan Malam Hari","number":17,"name":"سورة الإسراء","englishName":"Al-Israa","englishNameTranslation":"The Night Journey","revelationType":"Meccan","numberOfAyahs":111},{"idRevelationType":"Mekah","idNameTranslation":"Goa","number":18,"name":"سورة الكهف","englishName":"Al-Kahf","englishNameTranslation":"The Cave","revelationType":"Meccan","numberOfAyahs":110},{"idRevelationType":"Mekah","idNameTranslation":"Maryam","number":19,"name":"سورة مريم","englishName":"Maryam","englishNameTranslation":"Mary","revelationType":"Meccan","numberOfAyahs":98},{"idRevelationType":"Mekah","idNameTranslation":"Taha","number":20,"name":"سورة طه","englishName":"Taa-Haa","englishNameTranslation":"Taa-Haa","revelationType":"Meccan","numberOfAyahs":135},{"idRevelationType":"Mekah","idNameTranslation":"Para Nabi","number":21,"name":"سورة الأنبياء","englishName":"Al-Anbiyaa","englishNameTranslation":"The Prophets","revelationType":"Meccan","numberOfAyahs":112},{"idRevelationType":"Madinah","idNameTranslation":"Haji","number":22,"name":"سورة الحج","englishName":"Al-Hajj","englishNameTranslation":"The Pilgrimage","revelationType":"Medinan","numberOfAyahs":78},{"idRevelationType":"Mekah","idNameTranslation":"Orang-Orang Mukmin","number":23,"name":"سورة المؤمنون","englishName":"Al-Muminoon","englishNameTranslation":"The Believers","revelationType":"Meccan","numberOfAyahs":118},{"idRevelationType":"Madinah","idNameTranslation":"Cahaya","number":24,"name":"سورة النور","englishName":"An-Noor","englishNameTranslation":"The Light","revelationType":"Medinan","numberOfAyahs":64},{"idRevelationType":"Mekah","idNameTranslation":"Pembeda","number":25,"name":"سورة الفرقان","englishName":"Al-Furqaan","englishNameTranslation":"The Criterion","revelationType":"Meccan","numberOfAyahs":77},{"idRevelationType":"Mekah","idNameTranslation":"Para Penyair","number":26,"name":"سورة الشعراء","englishName":"Ash-Shu'araa","englishNameTranslation":"The Poets","revelationType":"Meccan","numberOfAyahs":227},{"idRevelationType":"Mekah","idNameTranslation":"Semut-semut","number":27,"name":"سورة النمل","englishName":"An-Naml","englishNameTranslation":"The Ant","revelationType":"Meccan","numberOfAyahs":93},{"idRevelationType":"Mekah","idNameTranslation":"Kisah-Kisah","number":28,"name":"سورة القصص","englishName":"Al-Qasas","englishNameTranslation":"The Stories","revelationType":"Meccan","numberOfAyahs":88},{"idRevelationType":"Mekah","idNameTranslation":"Laba-Laba","number":29,"name":"سورة العنكبوت","englishName":"Al-Ankaboot","englishNameTranslation":"The Spider","revelationType":"Meccan","numberOfAyahs":69},{"idRevelationType":"Mekah","idNameTranslation":"Romawi","number":30,"name":"سورة الروم","englishName":"Ar-Room","englishNameTranslation":"The Romans","revelationType":"Meccan","numberOfAyahs":60},{"idRevelationType":"Mekah","idNameTranslation":"Luqman","number":31,"name":"سورة لقمان","englishName":"Luqman","englishNameTranslation":"Luqman","revelationType":"Meccan","numberOfAyahs":34},{"idRevelationType":"Mekah","idNameTranslation":"Sajdah","number":32,"name":"سورة السجدة","englishName":"As-Sajda","englishNameTranslation":"The Prostration","revelationType":"Meccan","numberOfAyahs":30},{"idRevelationType":"Madinah","idNameTranslation":"Golongan Yang Bersekutu","number":33,"name":"سورة الأحزاب","englishName":"Al-Ahzaab","englishNameTranslation":"The Clans","revelationType":"Medinan","numberOfAyahs":73},{"idRevelationType":"Mekah","idNameTranslation":"Saba'","number":34,"name":"سورة سَبَأ","englishName":"Saba","englishNameTranslation":"Sheba","revelationType":"Meccan","numberOfAyahs":54},{"idRevelationType":"Mekah","idNameTranslation":"Maha Pencipta","number":35,"name":"سورة فاطر","englishName":"Faatir","englishNameTranslation":"The Originator","revelationType":"Meccan","numberOfAyahs":45},{"idRevelationType":"Mekah","idNameTranslation":"Yasin","number":36,"name":"سورة يس","englishName":"Yaseen","englishNameTranslation":"Yaseen","revelationType":"Meccan","numberOfAyahs":83},{"idRevelationType":"Mekah","idNameTranslation":"Barisan-Barisan","number":37,"name":"سورة الصافات","englishName":"As-Saaffaat","englishNameTranslation":"Those drawn up in Ranks","revelationType":"Meccan","numberOfAyahs":182},{"idRevelationType":"Mekah","idNameTranslation":"Sad","number":38,"name":"سورة ص","englishName":"Saad","englishNameTranslation":"The letter Saad","revelationType":"Meccan","numberOfAyahs":88},{"idRevelationType":"Mekah","idNameTranslation":"Rombongan","number":39,"name":"سورة الزمر","englishName":"Az-Zumar","englishNameTranslation":"The Groups","revelationType":"Meccan","numberOfAyahs":75},{"idRevelationType":"Mekah","idNameTranslation":"Maha Pengampun","number":40,"name":"سورة غافر","englishName":"Ghafir","englishNameTranslation":"The Forgiver","revelationType":"Meccan","numberOfAyahs":85},{"idRevelationType":"Mekah","idNameTranslation":"Yang Dijelaskan","number":41,"name":"سورة فصلت","englishName":"Fussilat","englishNameTranslation":"Explained in detail","revelationType":"Meccan","numberOfAyahs":54},{"idRevelationType":"Mekah","idNameTranslation":"Musyawarah","number":42,"name":"سورة الشورى","englishName":"Ash-Shura","englishNameTranslation":"Consultation","revelationType":"Meccan","numberOfAyahs":53},{"idRevelationType":"Mekah","idNameTranslation":"Perhiasan","number":43,"name":"سورة الزخرف","englishName":"Az-Zukhruf","englishNameTranslation":"Ornaments of gold","revelationType":"Meccan","numberOfAyahs":89},{"idRevelationType":"Mekah","idNameTranslation":"Kabut","number":44,"name":"سورة الدخان","englishName":"Ad-Dukhaan","englishNameTranslation":"The Smoke","revelationType":"Meccan","numberOfAyahs":59},{"idRevelationType":"Mekah","idNameTranslation":"Berlutut","number":45,"name":"سورة الجاثية","englishName":"Al-Jaathiya","englishNameTranslation":"Crouching","revelationType":"Meccan","numberOfAyahs":37},{"idRevelationType":"Mekah","idNameTranslation":"Bukit Pasir","number":46,"name":"سورة الأحقاف","englishName":"Al-Ahqaf","englishNameTranslation":"The Dunes","revelationType":"Meccan","numberOfAyahs":35},{"idRevelationType":"Madinah","idNameTranslation":"Muhammad","number":47,"name":"سورة محمد","englishName":"Muhammad","englishNameTranslation":"Muhammad","revelationType":"Medinan","numberOfAyahs":38},{"idRevelationType":"Madinah","idNameTranslation":"Kemenangan","number":48,"name":"سورة الفتح","englishName":"Al-Fath","englishNameTranslation":"The Victory","revelationType":"Medinan","numberOfAyahs":29},{"idRevelationType":"Madinah","idNameTranslation":"Kamar-Kamar","number":49,"name":"سورة الحجرات","englishName":"Al-Hujuraat","englishNameTranslation":"The Inner Apartments","revelationType":"Medinan","numberOfAyahs":18},{"idRevelationType":"Mekah","idNameTranslation":"Qaf","number":50,"name":"سورة ق","englishName":"Qaaf","englishNameTranslation":"The letter Qaaf","revelationType":"Meccan","numberOfAyahs":45},{"idRevelationType":"Mekah","idNameTranslation":"Angin yang Menerbangkan","number":51,"name":"سورة الذاريات","englishName":"Adh-Dhaariyat","englishNameTranslation":"The Winnowing Winds","revelationType":"Meccan","numberOfAyahs":60},{"idRevelationType":"Mekah","idNameTranslation":"Bukit Tursina","number":52,"name":"سورة الطور","englishName":"At-Tur","englishNameTranslation":"The Mount","revelationType":"Meccan","numberOfAyahs":49},{"idRevelationType":"Mekah","idNameTranslation":"Bintang","number":53,"name":"سورة النجم","englishName":"An-Najm","englishNameTranslation":"The Star","revelationType":"Meccan","numberOfAyahs":62},{"idRevelationType":"Mekah","idNameTranslation":"Bulan","number":54,"name":"سورة القمر","englishName":"Al-Qamar","englishNameTranslation":"The Moon","revelationType":"Meccan","numberOfAyahs":55},{"idRevelationType":"Madinah","idNameTranslation":"Maha Pengasih","number":55,"name":"سورة الرحمن","englishName":"Ar-Rahmaan","englishNameTranslation":"The Beneficent","revelationType":"Medinan","numberOfAyahs":78},{"idRevelationType":"Mekah","idNameTranslation":"Hari Kiamat","number":56,"name":"سورة الواقعة","englishName":"Al-Waaqia","englishNameTranslation":"The Inevitable","revelationType":"Meccan","numberOfAyahs":96},{"idRevelationType":"Madinah","idNameTranslation":"Besi","number":57,"name":"سورة الحديد","englishName":"Al-Hadid","englishNameTranslation":"The Iron","revelationType":"Medinan","numberOfAyahs":29},{"idRevelationType":"Madinah","idNameTranslation":"Gugatan","number":58,"name":"سورة المجادلة","englishName":"Al-Mujaadila","englishNameTranslation":"The Pleading Woman","revelationType":"Medinan","numberOfAyahs":22},{"idRevelationType":"Madinah","idNameTranslation":"Pengusiran","number":59,"name":"سورة الحشر","englishName":"Al-Hashr","englishNameTranslation":"The Exile","revelationType":"Medinan","numberOfAyahs":24},{"idRevelationType":"Madinah","idNameTranslation":"Wanita Yang Diuji","number":60,"name":"سورة الممتحنة","englishName":"Al-Mumtahana","englishNameTranslation":"She that is to be examined","revelationType":"Medinan","numberOfAyahs":13},{"idRevelationType":"Madinah","idNameTranslation":"Barisan","number":61,"name":"سورة الصف","englishName":"As-Saff","englishNameTranslation":"The Ranks","revelationType":"Medinan","numberOfAyahs":14},{"idRevelationType":"Madinah","idNameTranslation":"Jumat","number":62,"name":"سورة الجمعة","englishName":"Al-Jumu'a","englishNameTranslation":"Friday","revelationType":"Medinan","numberOfAyahs":11},{"idRevelationType":"Madinah","idNameTranslation":"Orang-Orang Munafik","number":63,"name":"سورة المنافقون","englishName":"Al-Munaafiqoon","englishNameTranslation":"The Hypocrites","revelationType":"Medinan","numberOfAyahs":11},{"idRevelationType":"Madinah","idNameTranslation":"Pengungkapan Kesalahan","number":64,"name":"سورة التغابن","englishName":"At-Taghaabun","englishNameTranslation":"Mutual Disillusion","revelationType":"Medinan","numberOfAyahs":18},{"idRevelationType":"Madinah","idNameTranslation":"Talak","number":65,"name":"سورة الطلاق","englishName":"At-Talaaq","englishNameTranslation":"Divorce","revelationType":"Medinan","numberOfAyahs":12},{"idRevelationType":"Madinah","idNameTranslation":"Pengharaman","number":66,"name":"سورة التحريم","englishName":"At-Tahrim","englishNameTranslation":"The Prohibition","revelationType":"Medinan","numberOfAyahs":12},{"idRevelationType":"Mekah","idNameTranslation":"Kerajaan","number":67,"name":"سورة الملك","englishName":"Al-Mulk","englishNameTranslation":"The Sovereignty","revelationType":"Meccan","numberOfAyahs":30},{"idRevelationType":"Mekah","idNameTranslation":"Pena","number":68,"name":"سورة القلم","englishName":"Al-Qalam","englishNameTranslation":"The Pen","revelationType":"Meccan","numberOfAyahs":52},{"idRevelationType":"Mekah","idNameTranslation":"Hari Kiamat","number":69,"name":"سورة الحاقة","englishName":"Al-Haaqqa","englishNameTranslation":"The Reality","revelationType":"Meccan","numberOfAyahs":52},{"idRevelationType":"Mekah","idNameTranslation":"Tempat Naik","number":70,"name":"سورة المعارج","englishName":"Al-Ma'aarij","englishNameTranslation":"The Ascending Stairways","revelationType":"Meccan","numberOfAyahs":44},{"idRevelationType":"Mekah","idNameTranslation":"Nuh","number":71,"name":"سورة نوح","englishName":"Nooh","englishNameTranslation":"Noah","revelationType":"Meccan","numberOfAyahs":28},{"idRevelationType":"Mekah","idNameTranslation":"Jin","number":72,"name":"سورة الجن","englishName":"Al-Jinn","englishNameTranslation":"The Jinn","revelationType":"Meccan","numberOfAyahs":28},{"idRevelationType":"Mekah","idNameTranslation":"Orang Yang Berselimut","number":73,"name":"سورة المزمل","englishName":"Al-Muzzammil","englishNameTranslation":"The Enshrouded One","revelationType":"Meccan","numberOfAyahs":20},{"idRevelationType":"Mekah","idNameTranslation":"Orang Yang Berkemul","number":74,"name":"سورة المدثر","englishName":"Al-Muddaththir","englishNameTranslation":"The Cloaked One","revelationType":"Meccan","numberOfAyahs":56},{"idRevelationType":"Mekah","idNameTranslation":"Hari Kiamat","number":75,"name":"سورة القيامة","englishName":"Al-Qiyaama","englishNameTranslation":"The Resurrection","revelationType":"Meccan","numberOfAyahs":40},{"idRevelationType":"Madinah","idNameTranslation":"Manusia","number":76,"name":"سورة الانسان","englishName":"Al-Insaan","englishNameTranslation":"Man","revelationType":"Medinan","numberOfAyahs":31},{"idRevelationType":"Mekah","idNameTranslation":"Malaikat Yang Diutus","number":77,"name":"سورة المرسلات","englishName":"Al-Mursalaat","englishNameTranslation":"The Emissaries","revelationType":"Meccan","numberOfAyahs":50},{"idRevelationType":"Mekah","idNameTranslation":"Berita Besar","number":78,"name":"سورة النبأ","englishName":"An-Naba","englishNameTranslation":"The Announcement","revelationType":"Meccan","numberOfAyahs":40},{"idRevelationType":"Mekah","idNameTranslation":"Malaikat Yang Mencabut","number":79,"name":"سورة النازعات","englishName":"An-Naazi'aat","englishNameTranslation":"Those who drag forth","revelationType":"Meccan","numberOfAyahs":46},{"idRevelationType":"Mekah","idNameTranslation":"Bermuka Masam","number":80,"name":"سورة عبس","englishName":"Abasa","englishNameTranslation":"He frowned","revelationType":"Meccan","numberOfAyahs":42},{"idRevelationType":"Mekah","idNameTranslation":"Penggulungan","number":81,"name":"سورة التكوير","englishName":"At-Takwir","englishNameTranslation":"The Overthrowing","revelationType":"Meccan","numberOfAyahs":29},{"idRevelationType":"Mekah","idNameTranslation":"Terbelah","number":82,"name":"سورة الإنفطار","englishName":"Al-Infitaar","englishNameTranslation":"The Cleaving","revelationType":"Meccan","numberOfAyahs":19},{"idRevelationType":"Mekah","idNameTranslation":"Orang-Orang Curang","number":83,"name":"سورة المطففين","englishName":"Al-Mutaffifin","englishNameTranslation":"Defrauding","revelationType":"Meccan","numberOfAyahs":36},{"idRevelationType":"Mekah","idNameTranslation":"Terbelah","number":84,"name":"سورة الإنشقاق","englishName":"Al-Inshiqaaq","englishNameTranslation":"The Splitting Open","revelationType":"Meccan","numberOfAyahs":25},{"idRevelationType":"Mekah","idNameTranslation":"Gugusan Bintang","number":85,"name":"سورة البروج","englishName":"Al-Burooj","englishNameTranslation":"The Constellations","revelationType":"Meccan","numberOfAyahs":22},{"idRevelationType":"Mekah","idNameTranslation":"Yang Datang Di Malam Hari","number":86,"name":"سورة الطارق","englishName":"At-Taariq","englishNameTranslation":"The Morning Star","revelationType":"Meccan","numberOfAyahs":17},{"idRevelationType":"Mekah","idNameTranslation":"Maha Tinggi","number":87,"name":"سورة الأعلى","englishName":"Al-A'laa","englishNameTranslation":"The Most High","revelationType":"Meccan","numberOfAyahs":19},{"idRevelationType":"Mekah","idNameTranslation":"Hari Kiamat","number":88,"name":"سورة الغاشية","englishName":"Al-Ghaashiya","englishNameTranslation":"The Overwhelming","revelationType":"Meccan","numberOfAyahs":26},{"idRevelationType":"Mekah","idNameTranslation":"Fajar","number":89,"name":"سورة الفجر","englishName":"Al-Fajr","englishNameTranslation":"The Dawn","revelationType":"Meccan","numberOfAyahs":30},{"idRevelationType":"Mekah","idNameTranslation":"Negeri","number":90,"name":"سورة البلد","englishName":"Al-Balad","englishNameTranslation":"The City","revelationType":"Meccan","numberOfAyahs":20},{"idRevelationType":"Mekah","idNameTranslation":"Matahari","number":91,"name":"سورة الشمس","englishName":"Ash-Shams","englishNameTranslation":"The Sun","revelationType":"Meccan","numberOfAyahs":15},{"idRevelationType":"Mekah","idNameTranslation":"Malam","number":92,"name":"سورة الليل","englishName":"Al-Lail","englishNameTranslation":"The Night","revelationType":"Meccan","numberOfAyahs":21},{"idRevelationType":"Mekah","idNameTranslation":"Duha","number":93,"name":"سورة الضحى","englishName":"Ad-Dhuhaa","englishNameTranslation":"The Morning Hours","revelationType":"Meccan","numberOfAyahs":11},{"idRevelationType":"Mekah","idNameTranslation":"Lapang","number":94,"name":"سورة الشرح","englishName":"Ash-Sharh","englishNameTranslation":"The Consolation","revelationType":"Meccan","numberOfAyahs":8},{"idRevelationType":"Mekah","idNameTranslation":"Buah Tin","number":95,"name":"سورة التين","englishName":"At-Tin","englishNameTranslation":"The Fig","revelationType":"Meccan","numberOfAyahs":8},{"idRevelationType":"Mekah","idNameTranslation":"Segumpal Darah","number":96,"name":"سورة العلق","englishName":"Al-Alaq","englishNameTranslation":"The Clot","revelationType":"Meccan","numberOfAyahs":19},{"idRevelationType":"Mekah","idNameTranslation":"Kemuliaan","number":97,"name":"سورة القدر","englishName":"Al-Qadr","englishNameTranslation":"The Power, Fate","revelationType":"Meccan","numberOfAyahs":5},{"idRevelationType":"Madinah","idNameTranslation":"Bukti Nyata","number":98,"name":"سورة البينة","englishName":"Al-Bayyina","englishNameTranslation":"The Evidence","revelationType":"Medinan","numberOfAyahs":8},{"idRevelationType":"Madinah","idNameTranslation":"Guncangan","number":99,"name":"سورة الزلزلة","englishName":"Az-Zalzala","englishNameTranslation":"The Earthquake","revelationType":"Medinan","numberOfAyahs":8},{"idRevelationType":"Mekah","idNameTranslation":"Kuda Yang Berlari Kencang","number":100,"name":"سورة العاديات","englishName":"Al-Aadiyaat","englishNameTranslation":"The Chargers","revelationType":"Meccan","numberOfAyahs":11},{"idRevelationType":"Mekah","idNameTranslation":"Hari Kiamat","number":101,"name":"سورة القارعة","englishName":"Al-Qaari'a","englishNameTranslation":"The Calamity","revelationType":"Meccan","numberOfAyahs":11},{"idRevelationType":"Mekah","idNameTranslation":"Bermegah-Megahan","number":102,"name":"سورة التكاثر","englishName":"At-Takaathur","englishNameTranslation":"Competition","revelationType":"Meccan","numberOfAyahs":8},{"idRevelationType":"Mekah","idNameTranslation":"Asar","number":103,"name":"سورة العصر","englishName":"Al-Asr","englishNameTranslation":"The Declining Day, Epoch","revelationType":"Meccan","numberOfAyahs":3},{"idRevelationType":"Mekah","idNameTranslation":"Pengumpat","number":104,"name":"سورة الهمزة","englishName":"Al-Humaza","englishNameTranslation":"The Traducer","revelationType":"Meccan","numberOfAyahs":9},{"idRevelationType":"Mekah","idNameTranslation":"Gajah","number":105,"name":"سورة الفيل","englishName":"Al-Fil","englishNameTranslation":"The Elephant","revelationType":"Meccan","numberOfAyahs":5},{"idRevelationType":"Mekah","idNameTranslation":"Quraisy","number":106,"name":"سورة قريش","englishName":"Quraish","englishNameTranslation":"Quraysh","revelationType":"Meccan","numberOfAyahs":4},{"idRevelationType":"Mekah","idNameTranslation":"Barang Yang Berguna","number":107,"name":"سورة الماعون","englishName":"Al-Maa'un","englishNameTranslation":"Almsgiving","revelationType":"Meccan","numberOfAyahs":7},{"idRevelationType":"Mekah","idNameTranslation":"Pemberian Yang Banyak","number":108,"name":"سورة الكوثر","englishName":"Al-Kawthar","englishNameTranslation":"Abundance","revelationType":"Meccan","numberOfAyahs":3},{"idRevelationType":"Mekah","idNameTranslation":"Orang-Orang kafir","number":109,"name":"سورة الكافرون","englishName":"Al-Kaafiroon","englishNameTranslation":"The Disbelievers","revelationType":"Meccan","numberOfAyahs":6},{"idRevelationType":"Madinah","idNameTranslation":"Pertolongan","number":110,"name":"سورة النصر","englishName":"An-Nasr","englishNameTranslation":"Divine Support","revelationType":"Medinan","numberOfAyahs":3},{"idRevelationType":"Mekah","idNameTranslation":"Api Yang Bergejolak","number":111,"name":"سورة المسد","englishName":"Al-Masad","englishNameTranslation":"The Palm Fibre","revelationType":"Meccan","numberOfAyahs":5},{"idRevelationType":"Mekah","idNameTranslation":"Ikhlas","number":112,"name":"سورة الإخلاص","englishName":"Al-Ikhlaas","englishNameTranslation":"Sincerity","revelationType":"Meccan","numberOfAyahs":4},{"idRevelationType":"Mekah","idNameTranslation":"Subuh","number":113,"name":"سورة الفلق","englishName":"Al-Falaq","englishNameTranslation":"The Dawn","revelationType":"Meccan","numberOfAyahs":5},{"idRevelationType":"Mekah","idNameTranslation":"Manusia","number":114,"name":"سورة الناس","englishName":"An-Naas","englishNameTranslation":"Mankind","revelationType":"Meccan","numberOfAyahs":6}]